saipravega-0.3.4.dist-info/METADATA
saipravega-0.3.4.dist-info/WHEEL
pravega_client/__init__.py
pravega_client/pravega_client.cp311-win_amd64.pyd
saipravega-0.3.4.dist-info/RECORD
