Metadata-Version: 2.1
Name: saipravega
Version: 0.3.4
Summary: Pravega client
Keywords: streaming,client,pravega
Author: Pravega Community
License: Apache-2.0
Project-URL: Source Code, https://github.com/kotlasaicharanreddy/pravega-client-rust
